arcane/firebase.py
arcane_firebase-0.2.0.dist-info/WHEEL
arcane_firebase-0.2.0.dist-info/METADATA
arcane_firebase-0.2.0.dist-info/RECORD
